opinionhub/__init__.py
opinionhub/core/__init__.py
opinionhub/core/llm.cpython-312-x86_64-linux-gnu.so
opinionhub/task/__init__.py
opinionhub/task/correlation_judge.cpython-312-x86_64-linux-gnu.so
opinionhub-0.0.0.15.dist-info/METADATA
opinionhub-0.0.0.15.dist-info/WHEEL
opinionhub-0.0.0.15.dist-info/top_level.txt
opinionhub-0.0.0.15.dist-info/zip-safe
opinionhub-0.0.0.15.dist-info/RECORD
